redshift_utils.py
sagemaker_redshift-0.2.0.dist-info/LICENSE
sagemaker_redshift-0.2.0.dist-info/METADATA
sagemaker_redshift-0.2.0.dist-info/WHEEL
sagemaker_redshift-0.2.0.dist-info/top_level.txt
sagemaker_redshift-0.2.0.dist-info/RECORD
