Metadata-Version: 2.1
Name: sagemaker-redshift
Version: 0.2.0
Summary: A Python utility library for Redshift data operations within SageMaker, enabling seamless UNLOAD and COPY operations between Redshift and S3
Author-email: Martin Contreras <martincontrerasur@gmail.com>
License: MIT
Project-URL: Homepage, https://github.com/martin-conur/sagemaker-redshift
Project-URL: Repository, https://github.com/martin-conur/sagemaker-redshift
Classifier: Development Status :: 4 - Beta
Classifier: Intended Audience :: Developers
Classifier: Topic :: Software Development :: Libraries :: Python Modules
Classifier: Topic :: Database
Classifier: License :: OSI Approved :: MIT License
Classifier: Programming Language :: Python :: 3
Classifier: Programming Language :: Python :: 3.7
Classifier: Programming Language :: Python :: 3.8
Classifier: Programming Language :: Python :: 3.9
Classifier: Programming Language :: Python :: 3.10
Classifier: Programming Language :: Python :: 3.11
Classifier: Operating System :: OS Independent
Requires-Python: >=3.7
License-File: LICENSE
Requires-Dist: boto3>=1.26.0
Requires-Dist: botocore>=1.29.0
Requires-Dist: polars>=0.19.0
Requires-Dist: sagemaker>=2.0.0
